{
    "images": [
        {
            "id": 1,
            "file_name": "/home/sparkle79/pypro/PoVER/swimXYZ/imgs/000114.jpg",
            "width": 640,
            "height": 480
        }
    ],
    "annotations": [
        {
            "id": 1,
            "image_id": 1,
            "category_id": 1,
            "keypoints": [
                900.703125,
                834.8572387695312,
                0.41488978266716003,
                928.12109375,
                848.7093505859375,
                0.30774208903312683,
                879.411865234375,
                851.077880859375,
                0.46673423051834106,
                794.7584228515625,
                594.8486328125,
                0.22707395255565643,
                817.314697265625,
                633.0914306640625,
                0.2577134966850281,
                767.683349609375,
                579.0601806640625,
                0.24544882774353027,
                725.697998046875,
                583.272216796875,
                0.32791948318481445,
                801.8436279296875,
                554.9013671875,
                0.5585773587226868,
                716.1387939453125,
                552.55517578125,
                0.4852815270423889,
                762.17041015625,
                551.0325927734375,
                0.4318658113479614,
                661.1669921875,
                547.904052734375,
                0.47551125288009644,
                839.3460693359375,
                552.34033203125,
                0.30957749485969543,
                814.8558349609375,
                560.8182373046875,
                0.32957538962364197,
                822.0791015625,
                568.0799560546875,
                0.3234175145626068,
                771.602783203125,
                571.2796630859375,
                0.31922978162765503,
                683.4696044921875,
                522.603759765625,
                0.38571897149086,
                632.956787109375,
                529.8138427734375,
                0.5697540044784546
            ],
            "num_keypoints": 17,
            "bbox": [
                50,
                200,
                150,
                350
            ],
            "area": 52500,
            "iscrowd": 0
        }
    ],
    "categories": [
        {
            "id": 1,
            "name": "person",
            "supercategory": "person",
            "keypoints": [
                "nose",
                "left_eye",
                "right_eye",
                "left_ear",
                "right_ear",
                "left_shoulder",
                "right_shoulder",
                "left_elbow",
                "right_elbow",
                "left_wrist",
                "right_wrist",
                "left_hip",
                "right_hip",
                "left_knee",
                "right_knee",
                "left_ankle",
                "right_ankle"
            ],
            "skeleton": [
                [
                    1,
                    2
                ],
                [
                    1,
                    3
                ],
                [
                    2,
                    4
                ],
                [
                    3,
                    5
                ],
                [
                    6,
                    7
                ],
                [
                    6,
                    8
                ],
                [
                    7,
                    9
                ],
                [
                    8,
                    10
                ],
                [
                    9,
                    11
                ],
                [
                    12,
                    13
                ],
                [
                    12,
                    14
                ],
                [
                    13,
                    15
                ],
                [
                    14,
                    16
                ],
                [
                    15,
                    17
                ]
            ]
        }
    ]
}