{
    "images": [
        {
            "id": 1,
            "file_name": "/home/sparkle79/pypro/PoVER/swimXYZ/process/imgs/000112.jpg",
            "width": 640,
            "height": 480
        }
    ],
    "annotations": [
        {
            "id": 1,
            "image_id": 1,
            "category_id": 1,
            "keypoints": [
                736.5751953125,
                745.376220703125,
                0.4842388927936554,
                756.6929931640625,
                756.2646484375,
                0.47817471623420715,
                746.008056640625,
                755.7015380859375,
                0.5261731743812561,
                756.857421875,
                759.798583984375,
                0.4665321111679077,
                751.4866943359375,
                757.0328369140625,
                0.5741847157478333,
                757.115478515625,
                708.00830078125,
                0.5908060669898987,
                699.7548828125,
                712.53271484375,
                0.588494598865509,
                785.481689453125,
                664.68505859375,
                0.4776431918144226,
                618.293212890625,
                683.337158203125,
                0.40316277742385864,
                875.531005859375,
                566.228271484375,
                0.44818130135536194,
                452.8388671875,
                703.82568359375,
                0.36015188694000244,
                762.7408447265625,
                618.494873046875,
                0.5037897825241089,
                714.328125,
                639.6796875,
                0.49870461225509644,
                816.613037109375,
                606.1357421875,
                0.37704989314079285,
                803.0048828125,
                609.5980224609375,
                0.39648330211639404,
                871.601806640625,
                548.723876953125,
                0.4142589569091797,
                883.64453125,
                559.521240234375,
                0.3844430148601532
            ],
            "num_keypoints": 17,
            "bbox": [
                50,
                200,
                150,
                350
            ],
            "area": 52500,
            "iscrowd": 0
        }
    ],
    "categories": [
        {
            "id": 1,
            "name": "person",
            "supercategory": "person",
            "keypoints": [
                "nose",
                "left_eye",
                "right_eye",
                "left_ear",
                "right_ear",
                "left_shoulder",
                "right_shoulder",
                "left_elbow",
                "right_elbow",
                "left_wrist",
                "right_wrist",
                "left_hip",
                "right_hip",
                "left_knee",
                "right_knee",
                "left_ankle",
                "right_ankle"
            ],
            "skeleton": [
                [
                    1,
                    2
                ],
                [
                    1,
                    3
                ],
                [
                    2,
                    4
                ],
                [
                    3,
                    5
                ],
                [
                    6,
                    7
                ],
                [
                    6,
                    8
                ],
                [
                    7,
                    9
                ],
                [
                    8,
                    10
                ],
                [
                    9,
                    11
                ],
                [
                    12,
                    13
                ],
                [
                    12,
                    14
                ],
                [
                    13,
                    15
                ],
                [
                    14,
                    16
                ],
                [
                    15,
                    17
                ]
            ]
        }
    ]
}